lhltools/__init__.py
lhltools/async_tool.py
lhltools/decorator.py
lhltools/email.py
lhl_python_tools-0.0.1.dist-info/LICENSE
lhl_python_tools-0.0.1.dist-info/METADATA
lhl_python_tools-0.0.1.dist-info/WHEEL
lhl_python_tools-0.0.1.dist-info/top_level.txt
lhl_python_tools-0.0.1.dist-info/RECORD
